pySMS/__init__.py
pySMS/chromedriver.exe
pySMS/configparse.py
pySMS/excelparse.py
pySMS/handlers.py
pySMS/hook.py
pySMS/keys.py
pySMS/livery.py
pySMS/messagebox.py
pySMS/prompts.py
pySMS/selenium.py
pySMS/data/__init__.py
pySMS/data/ci_data_library.json.gz
pySMS/data/export.py
pySMS/excel/__init__.py
pySMS/excel/loadFile.py
pySMS/excel/parseFile.py
pySMS/excel/ui/__init__.py
pySMS/excel/ui/openfile.py
pySMS/googledrive/__init__.py
pySMS/googledrive/authenticate.py
pySMS/googledrive/manage.py
pySMS/html/__init__.py
pySMS/html/adjustment.html
pySMS/html/build.py
pySMS/html/casepage.html
pySMS/html/get.py
pySMS/html/login.html
pySMS/html/main.html
pySMS/html/orderpage.html
pySMS/html/orderpageline.html
pySMS/html/parse.py
pySMS/html/userpage.html
pySMS/html/writeconfig.py
pySMS/html/pathdata/__init__.py
pySMS/html/pathdata/adjustStock.py
pySMS/html/pathdata/loginPage.py
pySMS/html/pathdata/mainPage.py
pySMS/html/pathdata/prodChooser.py
pySMS/html/pathdata/siteSettings.py
pySMS/html/pathdata/stockTab.py
pySMS/html/pathdata/stockTabMutate.py
pySMS/html/pathdata/stockTabTable.py
pySMS/html/pathdata/userSettings.py
pySMS/html/pathdata/json/__init__.py
pySMS/html/pathdata/json/adjustStock.json
pySMS/html/pathdata/json/loginPage.json
pySMS/html/pathdata/json/mainPage.json
pySMS/html/pathdata/json/prodChooser.json
pySMS/html/pathdata/json/siteSettings.json
pySMS/html/pathdata/json/stockTab.json
pySMS/html/pathdata/json/stockTabMutate.json
pySMS/html/pathdata/json/stockTabTable.json
pySMS/html/pathdata/json/userSettings.json
pySMS/pgsql/__init__.py
pySMS/pgsql/build_library.py
pySMS/pgsql/cipher.py
pySMS/pgsql/load_data.py
pySMS/pgsql/postgres.py
pySMS/pgsql/sql/__init__.py
pySMS/pgsql/sql/ci_component_data.sql
pySMS/pgsql/sql/ci_kit_data.sql
pySMS/pgsql/sql/ci_piece_data.sql
pySMS/pgsql/sql/ci_tray_data.sql
pySMS/req/__init__.py
pySMS/req/ppb.py
pySMS/req/prereq.py
pySMS/req/verify.py
pySMS/ui/__init__.py
pySMS-2.1.4.dist-info/DESCRIPTION.rst
pySMS-2.1.4.dist-info/METADATA
pySMS-2.1.4.dist-info/RECORD
pySMS-2.1.4.dist-info/WHEEL
pySMS-2.1.4.dist-info/metadata.json
pySMS-2.1.4.dist-info/top_level.txt
