Metadata-Version: 2.0
Name: pySMS
Version: 2.1.4
Summary: ZSMS Python Tools
Home-page: UNKNOWN
Author: Ian Doarn
Author-email: ian.doarn@zimmerbiomet.com
License: UNKNOWN
Platform: UNKNOWN
